BioGauss_Distributions/Binomialdistribution.py
BioGauss_Distributions/Gaussiandistribution.py
BioGauss_Distributions/Generaldistribution.py
BioGauss_Distributions/__init__.py
BioGauss_Distributions-0.1.dist-info/METADATA
BioGauss_Distributions-0.1.dist-info/WHEEL
BioGauss_Distributions-0.1.dist-info/top_level.txt
BioGauss_Distributions-0.1.dist-info/RECORD
