Metadata-Version: 2.1
Name: BioGauss_Distributions
Version: 0.1
Summary: Gaussian and Binomial distributions
Author: Abdelrahman ashraf
Author-email: bodehatta@gmail.com
